sceneprogexec/__init__.py
sceneprogexec/exec.py
sceneprogexec-0.2.2.dist-info/METADATA
sceneprogexec-0.2.2.dist-info/WHEEL
sceneprogexec-0.2.2.dist-info/entry_points.txt
sceneprogexec-0.2.2.dist-info/top_level.txt
sceneprogexec-0.2.2.dist-info/RECORD
