Metadata-Version: 2.4
Name: sceneprogexec
Version: 0.2.2
Summary: A CLI and Python module for executing Blender scripts and managing Blender's Python environment. Built to support SceneProg projects.
Home-page: https://github.com/KunalMGupta/SceneProgExec
Author: Kunal Gupta
Classifier: Programming Language :: Python :: 3
Classifier: Environment :: Console
Classifier: Operating System :: OS Independent
Requires-Python: >=3.11
Dynamic: author
Dynamic: classifier
Dynamic: description
Dynamic: description-content-type
Dynamic: home-page
Dynamic: requires-python
Dynamic: summary
